localperf/__init__.py
localperf/cpu.py
localperf/gpu_torch.py
localperf/parallel.py
localperf/parallel_benchmark.py
localperf/core/__init__.py
localperf/core/compute.py
localperf/core/config.py
localperf/core/measuring.py
localperf/core/parallel_func.py
localperf/core/utils.py
localperf-1.4.1.dist-info/LICENSE
localperf-1.4.1.dist-info/METADATA
localperf-1.4.1.dist-info/WHEEL
localperf-1.4.1.dist-info/top_level.txt
localperf-1.4.1.dist-info/RECORD
