Metadata-Version: 2.1
Name: localperf
Version: 1.4.1
Summary: Measure of python performance in local.
Home-page: https://github.com/tboulet/Local-Python-Performance
Author: Timothé Boulet
Author-email: timothe.boulet0@gmail.com
License: MIT
Requires: numpy
Requires: joblib
Requires: matplotlib
Requires: tqdm
License-File: LICENSE
